Metadata-Version: 1.1
Name: aop
Version: 0.2.0
Summary: Aspect-oriented programming
Home-page: https://github.com/orsinium/advice
Author: @orsinium
Author-email: master_fess@mail.ru
License: UNKNOWN
Keywords: aop aspect oriented programming advice joinpoint patching import decorators logging testing extension
Platform: UNKNOWN
Classifier: Development Status :: 4 - Beta
Classifier: Intended Audience :: Developers
Classifier: License :: OSI Approved :: Apache Software License
Classifier: Programming Language :: Python :: 3
Classifier: Programming Language :: Python :: 3.5
Classifier: Programming Language :: Python :: 3.6
Classifier: Programming Language :: Python :: 3.7
Classifier: Topic :: Software Development
Classifier: Topic :: Software Development :: Interpreters
Classifier: Topic :: Software Development :: Libraries
Classifier: Topic :: Software Development :: Pre-processors
Classifier: Topic :: Software Development :: Testing
Classifier: Topic :: Software Development :: Testing :: Mocking
Classifier: Topic :: System :: Logging
Requires: attrs
